pyobjcryst/__init__.py
pyobjcryst/_pyobjcryst.cpython-313-x86_64-linux-gnu.so
pyobjcryst/atom.py
pyobjcryst/crystal.py
pyobjcryst/diffractiondatasinglecrystal.py
pyobjcryst/fourier.py
pyobjcryst/general.py
pyobjcryst/globaloptim.py
pyobjcryst/globals.py
pyobjcryst/indexing.py
pyobjcryst/io.py
pyobjcryst/lsq.py
pyobjcryst/molecule.py
pyobjcryst/polyhedron.py
pyobjcryst/powderpattern.py
pyobjcryst/pyobjcryst_app.py
pyobjcryst/radiation.py
pyobjcryst/refinableobj.py
pyobjcryst/reflectionprofile.py
pyobjcryst/scatterer.py
pyobjcryst/scatteringdata.py
pyobjcryst/scatteringpower.py
pyobjcryst/scatteringpowersphere.py
pyobjcryst/spacegroup.py
pyobjcryst/unitcell.py
pyobjcryst/utils.py
pyobjcryst/version.py
pyobjcryst/zscatterer.py
pyobjcryst.libs/libObjCryst-7405430a.so
pyobjcryst.libs/libboost_container-9d51bf69.so.1.88.0
pyobjcryst.libs/libboost_graph-866513d0.so.1.88.0
pyobjcryst.libs/libboost_python313-f75d3e36.so.1.88.0
pyobjcryst-2025.1.0.dist-info/METADATA
pyobjcryst-2025.1.0.dist-info/WHEEL
pyobjcryst-2025.1.0.dist-info/top_level.txt
pyobjcryst-2025.1.0.dist-info/RECORD
pyobjcryst-2025.1.0.dist-info/licenses/AUTHORS.rst
pyobjcryst-2025.1.0.dist-info/licenses/LICENSE-DANSE.rst
pyobjcryst-2025.1.0.dist-info/licenses/LICENSE.rst
