Metadata-Version: 2.4
Name: pyobjcryst
Version: 2025.1.0
Summary: Python bindings to the ObjCryst++ library.
Author: Christopher Farrow, Pavol Juhás
Author-email: Vincent-Favre-Nicolin <favre@esrf.fr>
Maintainer-email: "Simon J.L. Billinge group" <sb2896@columbia.edu>, Vincent-Favre-Nicolin <favre@esrf.fr>
Project-URL: Homepage, https://github.com/diffpy/pyobjcryst/
Project-URL: Issues, https://github.com/diffpy/pyobjcryst/issues/
Keywords: objcryst,atom structure crystallography,powder diffraction
Classifier: Development Status :: 5 - Production/Stable
Classifier: Environment :: Console
Classifier: Intended Audience :: Developers
Classifier: Intended Audience :: Education
Classifier: Intended Audience :: Science/Research
Classifier: License :: OSI Approved :: BSD License
Classifier: Operating System :: MacOS :: MacOS X
Classifier: Operating System :: Microsoft :: Windows
Classifier: Operating System :: POSIX
Classifier: Operating System :: Unix
Classifier: Programming Language :: C++
Classifier: Programming Language :: Python :: 3.11
Classifier: Programming Language :: Python :: 3.12
Classifier: Programming Language :: Python :: 3.13
Classifier: Topic :: Scientific/Engineering :: Physics
Classifier: Topic :: Scientific/Engineering :: Chemistry
Classifier: Topic :: Software Development :: Libraries
Requires-Python: <3.14,>=3.11
License-File: LICENSE-DANSE.rst
License-File: LICENSE.rst
License-File: AUTHORS.rst
Requires-Dist: setuptools
Requires-Dist: numpy
Dynamic: license-file
